README.md
py4js.py
setup.py
py4js.egg-info/PKG-INFO
py4js.egg-info/SOURCES.txt
py4js.egg-info/dependency_links.txt
py4js.egg-info/requires.txt
py4js.egg-info/top_level.txt