Metadata-Version: 2.1
Name: py4js
Version: 0.1.1
Summary: a fast and simple micro-framework for small web applications
Home-page: https://github.com/lixk/py4js
Author: Xiangkui Li
Author-email: 1749498702@qq.com
License: MIT Licence
Keywords: pip,py4js
Platform: any
